MANIFEST.in
README.md
setup.cfg
setup.py
ghobserver/__init__.py
ghobserver/notify.py
ghobserver/pipeline.py
ghobserver/update_commits.py
ghobserver.egg-info/PKG-INFO
ghobserver.egg-info/SOURCES.txt
ghobserver.egg-info/dependency_links.txt
ghobserver.egg-info/not-zip-safe
ghobserver.egg-info/requires.txt
ghobserver.egg-info/top_level.txt
ghobserver/api/__init__.py
ghobserver/api/queries/__init__.py
ghobserver/api/queries/get_commits.py
ghobserver/api/queries/repository.py
ghobserver/charts/__init__.py
ghobserver/charts/additions_deletions.py
ghobserver/charts/density.py
ghobserver/charts/heatmap.py
ghobserver/charts/punchcard.py
ghobserver/charts/timeline.py
ghobserver/db/__init__.py
ghobserver/get_path/__init__.py
ghobserver/get_path/__main__.py
ghobserver/static/app.js
ghobserver/static/blank.html
ghobserver/static/routes.js
ghobserver/static/style.css
ghobserver/static/vv.js
ghobserver/static/vvstore.js
ghobserver/static/charts/.gitinclude
ghobserver/static/img/notification.png
ghobserver/static/js/vega-embed3.js
ghobserver/static/js/vega-lite2.js
ghobserver/static/js/vega3.js
ghobserver/templates/activity.html
ghobserver/templates/activity_panel.html
ghobserver/templates/content.html
ghobserver/templates/head.html
ghobserver/templates/index.html
ghobserver/templates/panel.html
ghobserver/templates/sidebar.html
ghobserver/update_repo/__init__.py
ghobserver/update_repo/__main__.py
ghobserver/update_repo/update.py