Metadata-Version: 1.1
Name: ghobserver
Version: 0.1.2
Summary: Python package for Ghobserver
Home-page: https://github.com/synw/ghobserver
Author: synw
Author-email: synwe@yahoo.com
License: UNKNOWN
Download-URL: https://github.com/synw/ghobserver/releases/tag/0.1.2
Keywords: github
Platform: UNKNOWN
Classifier: Development Status :: 3 - Alpha
Classifier: Intended Audience :: Developers
Classifier: License :: OSI Approved :: MIT License
Classifier: Programming Language :: Python :: 3.6
